pixseg/__init__.py
pixseg/datasets/__init__.py
pixseg/datasets/ade20k.py
pixseg/datasets/bdd100k.py
pixseg/datasets/cityscapes.py
pixseg/datasets/coco_stuff.py
pixseg/datasets/dataset_registry.py
pixseg/datasets/lip.py
pixseg/datasets/mapillary.py
pixseg/datasets/voc_like.py
pixseg/learn/__init__.py
pixseg/learn/criteria.py
pixseg/learn/lr_schedule.py
pixseg/learn/optimization.py
pixseg/learn/weighting.py
pixseg/models/__init__.py
pixseg/models/bisenet.py
pixseg/models/deeplabv3.py
pixseg/models/enet.py
pixseg/models/fcn.py
pixseg/models/lraspp.py
pixseg/models/model_registry.py
pixseg/models/model_utils.py
pixseg/models/pspnet.py
pixseg/models/sfnet.py
pixseg/models/sfnet_lite.py
pixseg/models/upernet.py
pixseg/models/backbones/__init__.py
pixseg/models/backbones/backbone_utils.py
pixseg/models/backbones/mobilenet_v3.py
pixseg/models/backbones/resnet.py
pixseg/models/backbones/vgg.py
pixseg/models/backbones/xception.py
pixseg/pipeline/__init__.py
pixseg/pipeline/config.py
pixseg/pipeline/engine.py
pixseg/pipeline/logger.py
pixseg/pipeline/test_time.py
pixseg/pipeline/trainer.py
pixseg/utils/metrics.py
pixseg/utils/rng.py
pixseg/utils/transform.py
pixseg/utils/visual.py
pixseg-0.8.2.dist-info/METADATA
pixseg-0.8.2.dist-info/WHEEL
pixseg-0.8.2.dist-info/licenses/LICENSE
pixseg-0.8.2.dist-info/RECORD
