Metadata-Version: 2.4
Name: pixseg
Version: 0.8.2
Summary: A simple semantic segmentation package using PyTorch
Project-URL: Homepage, https://github.com/CyrusCKF/pixseg
Project-URL: Documentation, https://github.com/CyrusCKF/pixseg/blob/main/README.md
Project-URL: Repository, https://github.com/CyrusCKF/pixseg
Project-URL: Issues, https://github.com/CyrusCKF/pixseg/issues
Author-email: Cheung Ka Fai <cyrus.cheungkf@gmail.com>, m19990328@gmail.com
License-Expression: MIT
License-File: LICENSE
Keywords: pytorch,semantic segmentation
Classifier: Development Status :: 3 - Alpha
Classifier: Intended Audience :: Developers
Classifier: Intended Audience :: Education
Classifier: Intended Audience :: Science/Research
Classifier: Programming Language :: Python
Classifier: Programming Language :: Python :: 3.10
Classifier: Topic :: Scientific/Engineering
Classifier: Topic :: Scientific/Engineering :: Artificial Intelligence
Classifier: Topic :: Software Development
Classifier: Topic :: Software Development :: Libraries
Requires-Python: >=3.10
Requires-Dist: torch>=2.6.0
Requires-Dist: torchvision>=0.21.0
Provides-Extra: dev
Requires-Dist: build>=1.2.2; extra == 'dev'
Requires-Dist: h5py>=3.13.0; extra == 'dev'
Requires-Dist: jupyter>=1.1.1; extra == 'dev'
Requires-Dist: matplotlib>=3.10.0; extra == 'dev'
Requires-Dist: pytest-cov>=6.0.0; extra == 'dev'
Requires-Dist: pytest>=8.3.4; extra == 'dev'
Requires-Dist: scikit-learn>=1.6.1; extra == 'dev'
Requires-Dist: seaborn>=0.13.2; extra == 'dev'
Requires-Dist: tensorboard>=2.19.0; extra == 'dev'
Requires-Dist: toml>=0.10.2; extra == 'dev'
Requires-Dist: torchinfo>=1.8.0; extra == 'dev'
Requires-Dist: tqdm>=4.67.1; extra == 'dev'
Requires-Dist: twine>=6.1.0; extra == 'dev'
Requires-Dist: wandb>=0.19.6; extra == 'dev'
Provides-Extra: full
Requires-Dist: matplotlib>=3.10.0; extra == 'full'
Requires-Dist: scikit-learn>=1.6.1; extra == 'full'
Requires-Dist: seaborn>=0.13.2; extra == 'full'
Requires-Dist: tensorboard>=2.19.0; extra == 'full'
Requires-Dist: toml>=0.10.2; extra == 'full'
Requires-Dist: tqdm>=4.67.1; extra == 'full'
Requires-Dist: wandb>=0.19.6; extra == 'full'
